odoo/addons/hr_attendance_report_theoretical_time/README.rst
odoo/addons/hr_attendance_report_theoretical_time/__init__.py
odoo/addons/hr_attendance_report_theoretical_time/__manifest__.py
odoo/addons/hr_attendance_report_theoretical_time/i18n/bg.po
odoo/addons/hr_attendance_report_theoretical_time/i18n/de.po
odoo/addons/hr_attendance_report_theoretical_time/i18n/es.po
odoo/addons/hr_attendance_report_theoretical_time/i18n/fr.po
odoo/addons/hr_attendance_report_theoretical_time/i18n/hr_attendance_report_theoretical_time.pot
odoo/addons/hr_attendance_report_theoretical_time/i18n/it.po
odoo/addons/hr_attendance_report_theoretical_time/models/__init__.py
odoo/addons/hr_attendance_report_theoretical_time/models/calendar_public_holiday_line.py
odoo/addons/hr_attendance_report_theoretical_time/models/hr_attendance.py
odoo/addons/hr_attendance_report_theoretical_time/models/hr_employee.py
odoo/addons/hr_attendance_report_theoretical_time/models/hr_employee_public.py
odoo/addons/hr_attendance_report_theoretical_time/models/hr_leave.py
odoo/addons/hr_attendance_report_theoretical_time/models/hr_leave_type.py
odoo/addons/hr_attendance_report_theoretical_time/models/resource_calendar.py
odoo/addons/hr_attendance_report_theoretical_time/readme/CONFIGURE.md
odoo/addons/hr_attendance_report_theoretical_time/readme/CONTRIBUTORS.md
odoo/addons/hr_attendance_report_theoretical_time/readme/CREDITS.md
odoo/addons/hr_attendance_report_theoretical_time/readme/DESCRIPTION.md
odoo/addons/hr_attendance_report_theoretical_time/readme/INSTALL.md
odoo/addons/hr_attendance_report_theoretical_time/readme/ROADMAP.md
odoo/addons/hr_attendance_report_theoretical_time/readme/USAGE.md
odoo/addons/hr_attendance_report_theoretical_time/reports/__init__.py
odoo/addons/hr_attendance_report_theoretical_time/reports/hr_attendance_report_views.xml
odoo/addons/hr_attendance_report_theoretical_time/reports/hr_attendance_theoretical_time_report.py
odoo_addon_hr_attendance_report_theoretical_time-18.0.1.0.0.2.dist-info/METADATA
odoo_addon_hr_attendance_report_theoretical_time-18.0.1.0.0.2.dist-info/WHEEL
odoo_addon_hr_attendance_report_theoretical_time-18.0.1.0.0.2.dist-info/top_level.txt
odoo_addon_hr_attendance_report_theoretical_time-18.0.1.0.0.2.dist-info/RECORD
