Metadata-Version: 2.1
Name: odoo-addon-hr_attendance_report_theoretical_time
Version: 18.0.1.0.0.2
Requires-Python: >=3.10
Requires-Dist: odoo-addon-hr_holidays_public==18.0.*
Requires-Dist: odoo==18.0.*
Summary: Theoretical vs Attended Time Analysis
Home-page: https://github.com/OCA/hr-attendance
License: AGPL-3
Author: Tecnativa, Odoo Community Association (OCA)
Author-email: support@odoo-community.org
Classifier: Programming Language :: Python
Classifier: Framework :: Odoo
Classifier: Framework :: Odoo :: 18.0
Classifier: License :: OSI Approved :: GNU Affero General Public License v3
